pratica7/morse.v
module morse (in, out, reset, clk);

    input in, reset, clk;
    output reg [7:0] out;

    parameter A = 5'b00001, B = 5'b00010, C = 5'b00011, D = 5'b00100, E = 5'b00101, 
              F = 5'b00110, G = 5'b00111, H = 5'b01000, I = 5'b01001, J = 5'b01010,
              K = 5'b01011, L = 5'b01100, M = 5'b01101, N = 5'b01110, O = 5'b01111,
              P = 5'b10000, Q = 5'b10001, R = 5'b10010, S = 5'b10011, T = 5'b10100,
              U = 5'b10101, V = 5'b10110, W = 5'b10111, X = 5'b11000, Y = 5'b11001,
              Z = 5'b11010, IDLE = 5'bxxxxx;

    reg [5:0] state, next_state;

    always @(posedge clk) begin
        if (reset)
            state = IDLE;
        else
            state = next_state;        
    end

    always @(*) begin
        case (state)   
            IDLE: begin
                if (in)
                    next_state = E; 
                else
                    next_state = T; 
            end   
            E: begin
                if (in)
                    next_state = I; 
                else
                    next_state = A; 
            end
            A: begin
                if (in)
                    next_state = R; 
                else
                    next_state = W; 
            end
            R: begin
                if (in)
                    next_state = L; 
                else
                    next_state = IDLE;
            end
            W: begin
                if (in)
                    next_state = P; 
                else
                    next_state = J; 
            end
            I: begin
                if (in)
                    next_state = S; 
                else 
                    next_state = U; 
            end 
            S: begin
                if (in)
                    next_state = H; 
                else
                    next_state = V; 
            end
            U: begin
                if (in) 
                    next_state = F; 
                else 
                    next_state = IDLE;
            end
            T: begin
                if (in)
                    next_state = N; 
                else
                    next_state = M; 
            end
            M: begin
                if (in)
                    next_state = G; 
                else
                    next_state = O; 
            end
            G: begin
                if (in)
                    next_state = Z; 
                else
                    next_state = Q; 
            end
            N: begin
                if (in)
                    next_state = D; 
                else
                    next_state = K; 
            end
            D: begin
                if (in)
                    next_state = B; 
                else
                    next_state = X; 
            end
            K: begin
                if (in)
                    next_state = C; 
                else 
                    next_state = Y; 
            end
                             
            default: next_state = IDLE;
        endcase
        
    end

    always @(*) begin
        case (state)
            IDLE: out = 8'h00;
            A: out = 8'h41; 
            B: out = 8'h42; 
            C: out = 8'h43;
            D: out = 8'h44;
            E: out = 8'h45;
            F: out = 8'h46;
            G: out = 8'h47;
            H: out = 8'h48;
            I: out = 8'h49;
            J: out = 8'h4A;
            K: out = 8'h4B;
            L: out = 8'h4C;
            M: out = 8'h4D;
            N: out = 8'h4E;
            O: out = 8'h4F;
            P: out = 8'h50;
            Q: out = 8'h51;
            R: out = 8'h52;
            S: out = 8'h53;
            T: out = 8'h54;
            U: out = 8'h55;
            V: out = 8'h56;
            W: out = 8'h57;
            X: out = 8'h58;
            Y: out = 8'h59;
            Z: out = 8'h5A;
            default: next_state = IDLE;
        endcase
    end
endmodule

pratica7/morse_teste.v
`timescale 10ns/1ns
`include "morse.v"

module morse_teste;


    reg in, reset, clk;
    wire [7:0] out;
    morse uut(in, out, reset, clk);

    initial begin
        $dumpfile("morse.vcd");
        $dumpvars(0, morse_teste);

        in = 1;

        // LETRA A
        reset = 1; #10
        reset = 0; #10
        in = 1; #10     // .
        in = 0; #10 #10 // -

        // LETRA B
        reset = 1; #10 #10
        reset = 0; #10 #10
        in = 0; #10// -
        in = 1; #10 #10 // .
        #10 #10 // .
        #10 #10 // .

        // LETRA C
        in = 0; // -
        reset = 1; #10 #10
        reset = 0; #10 #10
        in = 1; #10 // .
        in = 0; #10 #10// -
        in = 1; #10 #10 // .
        
        // LETRA D (-..)
        reset = 1; #10;
        reset = 0; #10;
        in = 0; #10;     // Traço (-)
        in = 1; #10 #10; // Ponto (.)
        in = 1; #10 #10; // Ponto (.)

        // LETRA E (.)
        reset = 1; #10;
        reset = 0; #10;
        in = 1; #10;     // Ponto (.)

        // LETRA F (..-.)
        reset = 1; #10;
        reset = 0; #10;
        in = 1; #10;     // Ponto (.)
        in = 1; #10 #10; // Ponto (.)
        in = 0; #10 #10; // Traço (-)
        in = 1; #10 #10; // Ponto (.)

        // LETRA G (--.)
        reset = 1; #10;
        reset = 0; #10;
        in = 0; #10;     // Traço (-)
        in = 0; #10 #10; // Traço (-)
        in = 1; #10 #10; // Ponto (.)

        // LETRA H (....)
        reset = 1; #10;
        reset = 0; #10;
        in = 1; #10;     // Ponto (.)
        in = 1; #10 #10; // Ponto (.)
        in = 1; #10 #10; // Ponto (.)
        in = 1; #10 #10; // Ponto (.)

        // LETRA I (..)
        reset = 1; #10;
        reset = 0; #10;
        in = 1; #10;     // Ponto (.)
        in = 1; #10 #10; // Ponto (.)

        // LETRA J (.---)
        reset = 1; #10;
        reset = 0; #10;
        in = 1; #10;     // Ponto (.)
        in = 0; #10 #10; // Traço (-)
        in = 0; #10 #10; // Traço (-)
        in = 0; #10 #10; // Traço (-)

        // LETRA K (-.-)
        reset = 1; #10;
        reset = 0; #10;
        in = 0; #10;     // Traço (-)
        in = 1; #10 #10; // Ponto (.)
        in = 0; #10 #10; // Traço (-)

        // LETRA L (.-..)
        reset = 1; #10;
        reset = 0; #10;
        in = 1; #10;     // Ponto (.)
        in = 0; #10 #10; // Traço (-)
        in = 1; #10 #10; // Ponto (.)
        in = 1; #10 #10; // Ponto (.)

        // LETRA M (--)
        reset = 1; #10;
        reset = 0; #10;
        in = 0; #10;     // Traço (-)
        in = 0; #10 #10; // Traço (-)

        // LETRA N (-.)
        reset = 1; #10;
        reset = 0; #10;
        in = 0; #10;     // Traço (-)
        in = 1; #10 #10; // Ponto (.)

        // LETRA O (---)
        reset = 1; #10;
        reset = 0; #10;
        in = 0; #10;     // Traço (-)
        in = 0; #10 #10; // Traço (-)
        in = 0; #10 #10; // Traço (-)

        // LETRA P (.--.)
        reset = 1; #10;
        reset = 0; #10;
        in = 1; #10;     // Ponto (.)
        in = 0; #10 #10; // Traço (-)
        in = 0; #10 #10; // Traço (-)
        in = 1; #10 #10; // Ponto (.)

        // LETRA Q (--.-)
        reset = 1; #10;
        reset = 0; #10;
        in = 0; #10;     // Traço (-)
        in = 0; #10 #10; // Traço (-)
        in = 1; #10 #10; // Ponto (.)
        in = 0; #10 #10; // Traço (-)

        // LETRA R (.-.)
        reset = 1; #10;
        reset = 0; #10;
        in = 1; #10;     // Ponto (.)
        in = 0; #10 #10; // Traço (-)
        in = 1; #10 #10; // Ponto (.)

        // LETRA S (...)
        reset = 1; #10;
        reset = 0; #10;
        in = 1; #10;     // Ponto (.)
        in = 1; #10 #10; // Ponto (.)
        in = 1; #10 #10; // Ponto (.)

        // LETRA T (-)
        reset = 1; #10;
        reset = 0; #10;
        in = 0; #10;     // Traço (-)

        // LETRA U (..-)
        reset = 1; #10;
        reset = 0; #10;
        in = 1; #10;     // Ponto (.)
        in = 1; #10 #10; // Ponto (.)
        in = 0; #10 #10; // Traço (-)

        // LETRA V (...-)
        reset = 1; #10;
        reset = 0; #10;
        in = 1; #10;     // Ponto (.)
        in = 1; #10 #10; // Ponto (.)
        in = 1; #10 #10; // Ponto (.)
        in = 0; #10 #10; // Traço (-)

        // LETRA W (.--)
        reset = 1; #10;
        reset = 0; #10;
        in = 1; #10;     // Ponto (.)
        in = 0; #10 #10; // Traço (-)
        in = 0; #10 #10; // Traço (-)

        // LETRA X (-..-)
        reset = 1; #10;
        reset = 0; #10;
        in = 0; #10;     // Traço (-)
        in = 1; #10 #10; // Ponto (.)
        in = 1; #10 #10; // Ponto (.)
        in = 0; #10 #10; // Traço (-)

        // LETRA Y (-.--)
        reset = 1; #10;
        reset = 0; #10;
        in = 0; #10;     // Traço (-)
        in = 1; #10 #10; // Ponto (.)
        in = 0; #10 #10; // Traço (-)
        in = 0; #10 #10; // Traço (-)

        // LETRA Z (--..)
        reset = 1; #10;
        reset = 0; #10;
        in = 0; #10;     // Traço (-)
        in = 0; #10 #10; // Traço (-)
        in = 1; #10 #10; // Ponto (.)
        in = 1; #10 #10; // Ponto (.)
        
        #10
        $finish;
    end

    initial begin
        clk = 1;
        forever #10 clk = ~clk;
    end
    
endmodule

pratica7/morse.vcd
$date
	Tue Nov 26 03:31:46 2024
$end
$version
	Icarus Verilog
$end
$timescale
	1ns
$end
$scope module morse_teste $end
$var wire 8 ! out [7:0] $end
$var reg 1 " clk $end
$var reg 1 # in $end
$var reg 1 $ reset $end
$scope module uut $end
$var wire 1 " clk $end
$var wire 1 # in $end
$var wire 1 $ reset $end
$var parameter 5 % A $end
$var parameter 5 & B $end
$var parameter 5 ' C $end
$var parameter 5 ( D $end
$var parameter 5 ) E $end
$var parameter 5 * F $end
$var parameter 5 + G $end
$var parameter 5 , H $end
$var parameter 5 - I $end
$var parameter 5 . IDLE $end
$var parameter 5 / J $end
$var parameter 5 0 K $end
$var parameter 5 1 L $end
$var parameter 5 2 M $end
$var parameter 5 3 N $end
$var parameter 5 4 O $end
$var parameter 5 5 P $end
$var parameter 5 6 Q $end
$var parameter 5 7 R $end
$var parameter 5 8 S $end
$var parameter 5 9 T $end
$var parameter 5 : U $end
$var parameter 5 ; V $end
$var parameter 5 < W $end
$var parameter 5 = X $end
$var parameter 5 > Y $end
$var parameter 5 ? Z $end
$var reg 6 @ next_state [5:0] $end
$var reg 8 A out [7:0] $end
$var reg 6 B state [5:0] $end
$upscope $end
$upscope $end
$enddefinitions $end
$comment Show the parameter values. $end
$dumpall
b11010 ?
b11001 >
b11000 =
b10111 <
b10110 ;
b10101 :
b10100 9
b10011 8
b10010 7
b10001 6
b10000 5
b1111 4
b1110 3
b1101 2
b1100 1
b1011 0
b1010 /
bx .
b1001 -
b1000 ,
b111 +
b110 *
b101 )
b100 (
b11 '
b10 &
b1 %
$end
#0
$dumpvars
b0xxxxx B
b0 A
b101 @
1$
1#
1"
b0 !
$end
#100
0"
0$
#200
b1000101 !
b1000101 A
b1001 @
b101 B
1"
#300
b1 @
0"
0#
#400
b1000001 !
b1000001 A
b10111 @
b1 B
1"
#500
0"
1$
#600
b0 !
b0 A
b10100 @
b0xxxxx B
1"
#700
0"
0$
#800
b1010100 !
b1010100 A
b1101 @
b10100 B
1"
#900
0"
#1000
b1001110 !
b1001110 A
b1110 B
b100 @
1"
1#
#1100
0"
#1200
b1000100 !
b1000100 A
b10 @
b100 B
1"
#1300
0"
#1400
b1000010 !
b1000010 A
b0xxxxx @
b10 B
1"
#1500
0"
#1600
b0 !
b0 A
b10100 @
b0xxxxx B
1"
1$
0#
#1700
0"
#1800
b1010100 !
b1010100 A
b1101 @
b10100 B
1"
0$
#1900
0"
#2000
b1001110 !
b1001110 A
b1110 B
b100 @
1"
1#
#2100
b1011 @
0"
0#
#2200
b1001011 !
b1001011 A
b11001 @
b1011 B
1"
#2300
b11 @
0"
1#
#2400
b1000011 !
b1000011 A
b0xxxxx @
b11 B
1"
#2500
0"
1$
#2600
b0 !
b0 A
b101 @
b0xxxxx B
1"
0$
#2700
b10100 @
0"
0#
#2800
b1000101 !
b1000101 A
b101 B
b1001 @
1"
1#
#2900
0"
#3000
b1001001 !
b1001001 A
b10011 @
b1001 B
1"
#3100
0"
#3200
b0 !
b0 A
b101 @
b0xxxxx B
1"
1$
#3300
0"
0$
#3400
b1000101 !
b1000101 A
b1001 @
b101 B
1"
#3500
0"
1$
#3600
b1001001 !
b1001001 A
b10011 @
b1001 B
1"
0$
#3700
0"
#3800
b1010011 !
b1010011 A
b1000 @
b10011 B
1"
#3900
0"
#4000
b1010110 !
b1010110 A
b10110 B
b0xxxxx @
1"
0#
#4100
0"
#4200
b0 !
b0 A
b101 @
b0xxxxx B
1"
1#
#4300
0"
#4400
1"
1$
#4500
0"
0$
#4600
b1010100 !
b1010100 A
b10100 B
b1101 @
1"
0#
#4700
0"
#4800
b1001101 !
b1001101 A
b1111 @
b1101 B
1"
#4900
b111 @
0"
1#
#5000
b1000111 !
b1000111 A
b11010 @
b111 B
1"
#5100
0"
1$
#5200
b1011010 !
b1011010 A
b0xxxxx @
b11010 B
1"
0$
#5300
0"
#5400
b0 !
b0 A
b101 @
b0xxxxx B
1"
#5500
0"
#5600
b1000101 !
b1000101 A
b1001 @
b101 B
1"
#5700
0"
#5800
b1001001 !
b1001001 A
b10011 @
b1001 B
1"
#5900
0"
#6000
b0 !
b0 A
b101 @
b0xxxxx B
1"
1$
#6100
0"
0$
#6200
b1000101 !
b1000101 A
b1001 @
b101 B
1"
#6300
0"
#6400
b1001001 !
b1001001 A
b10011 @
b1001 B
1"
#6500
0"
1$
#6600
b1010011 !
b1010011 A
b1000 @
b10011 B
1"
0$
#6700
0"
#6800
b1010110 !
b1010110 A
b10110 B
b0xxxxx @
1"
0#
#6900
0"
#7000
b0 !
b0 A
b10100 @
b0xxxxx B
1"
#7100
0"
#7200
b1010100 !
b1010100 A
b1101 @
b10100 B
1"
#7300
0"
#7400
b0 !
b0 A
b10100 @
b0xxxxx B
1"
1$
#7500
0"
0$
#7600
b1010100 !
b1010100 A
b1101 @
b10100 B
1"
#7700
b1110 @
0"
1#
#7800
b1001110 !
b1001110 A
b100 @
b1110 B
1"
#7900
b1011 @
0"
0#
#8000
b1001011 !
b1001011 A
b11001 @
b1011 B
1"
#8100
0"
1$
#8200
b1011001 !
b1011001 A
b0xxxxx @
b11001 B
1"
0$
#8300
0"
1#
#8400
b0 !
b0 A
b10100 @
b0xxxxx B
1"
0#
#8500
0"
#8600
b1000101 !
b1000101 A
b101 B
b1001 @
1"
1#
#8700
0"
#8800
b1001001 !
b1001001 A
b10011 @
b1001 B
1"
#8900
0"
#9000
b0 !
b0 A
b101 @
b0xxxxx B
1"
1$
#9100
0"
0$
#9200
b1010100 !
b1010100 A
b10100 B
b1101 @
1"
0#
#9300
0"
#9400
b1001101 !
b1001101 A
b1111 @
b1101 B
1"
#9500
0"
1$
#9600
b1001111 !
b1001111 A
b0xxxxx @
b1111 B
1"
0$
#9700
0"
#9800
b0 !
b0 A
b101 @
b0xxxxx B
1"
1#
#9900
0"
#10000
1"
1$
#10100
0"
0$
#10200
b1010100 !
b1010100 A
b10100 B
b1101 @
1"
0#
#10300
0"
#10400
b1001101 !
b1001101 A
b1111 @
b1101 B
1"
#10500
0"
#10600
b1001111 !
b1001111 A
b0xxxxx @
b1111 B
1"
#10700
0"
1$
#10800
b0 !
b0 A
b10100 @
b0xxxxx B
1"
0$
#10900
b101 @
0"
1#
#11000
b1010100 !
b1010100 A
b10100 B
b1101 @
1"
0#
#11100
0"
#11200
b1001101 !
b1001101 A
b1111 @
b1101 B
1"
#11300
0"
#11400
b1000111 !
b1000111 A
b111 B
b11010 @
1"
1#
#11500
0"
#11600
b0 !
b0 A
b101 @
b0xxxxx B
1"
1$
#11700
0"
0$
#11800
b1010100 !
b1010100 A
b10100 B
b1101 @
1"
0#
#11900
0"
#12000
b1001101 !
b1001101 A
b1111 @
b1101 B
1"
#12100
b111 @
0"
1#
#12200
b1000111 !
b1000111 A
b11010 @
b111 B
1"
#12300
b10001 @
0"
0#
#12400
b1010001 !
b1010001 A
b0xxxxx @
b10001 B
1"
#12500
0"
1$
#12600
b0 !
b0 A
b10100 @
b0xxxxx B
1"
0$
#12700
b101 @
0"
1#
#12800
b1010100 !
b1010100 A
b10100 B
b1101 @
1"
0#
#12900
0"
#13000
b1001110 !
b1001110 A
b1110 B
b100 @
1"
1#
#13100
0"
#13200
b0 !
b0 A
b101 @
b0xxxxx B
1"
1$
#13300
0"
0$
#13400
b1000101 !
b1000101 A
b1001 @
b101 B
1"
#13500
0"
#13600
b1001001 !
b1001001 A
b10011 @
b1001 B
1"
#13700
0"
#13800
b1010011 !
b1010011 A
b1000 @
b10011 B
1"
#13900
0"
1$
#14000
b1001000 !
b1001000 A
b0xxxxx @
b1000 B
1"
0$
#14100
0"
0#
#14200
b0 !
b0 A
b10100 @
b0xxxxx B
1"
1$
#14300
0"
0$
#14400
b1000101 !
b1000101 A
b101 B
b1001 @
1"
1#
#14500
0"
#14600
b1001001 !
b1001001 A
b10011 @
b1001 B
1"
#14700
b10101 @
0"
0#
#14800
b1010101 !
b1010101 A
b0xxxxx @
b10101 B
1"
#14900
0"
1$
#15000
b0 !
b0 A
b10100 @
b0xxxxx B
1"
0$
#15100
b101 @
0"
1#
#15200
b1000101 !
b1000101 A
b1001 @
b101 B
1"
#15300
0"
#15400
b1001001 !
b1001001 A
b10011 @
b1001 B
1"
#15500
0"
#15600
b1010101 !
b1010101 A
b10101 B
b0xxxxx @
1"
0#
#15700
0"
#15800
b0 !
b0 A
b10100 @
b0xxxxx B
1"
1$
#15900
0"
0$
#16000
b1000101 !
b1000101 A
b101 B
b1001 @
1"
1#
#16100
b1 @
0"
0#
#16200
b1000001 !
b1000001 A
b10111 @
b1 B
1"
#16300
0"
#16400
b1010111 !
b1010111 A
b1010 @
b10111 B
1"
#16500
0"
1$
#16600
b1001010 !
b1001010 A
b0xxxxx @
b1010 B
1"
0$
#16700
0"
#16800
b0 !
b0 A
b101 @
b0xxxxx B
1"
1#
#16900
0"
#17000
b1000101 !
b1000101 A
b1001 @
b101 B
1"
#17100
0"
#17200
b1000001 !
b1000001 A
b1 B
b10111 @
1"
0#
#17300
0"
#17400
b0 !
b0 A
b10100 @
b0xxxxx B
1"
1$
#17500
0"
0$
#17600
b1010100 !
b1010100 A
b1101 @
b10100 B
1"
#17700
b1110 @
0"
1#
#17800
b1001110 !
b1001110 A
b100 @
b1110 B
1"
#17900
b1011 @
0"
0#
#18000
b1001011 !
b1001011 A
b11001 @
b1011 B
1"
#18100
0"
#18200
b1011001 !
b1011001 A
b0xxxxx @
b11001 B
1"
#18300
0"
1$
#18400
b0 !
b0 A
b10100 @
b0xxxxx B
1"
0$
#18500
0"
#18600
b1010100 !
b1010100 A
b1101 @
b10100 B
1"
#18700
0"
#18800
b1001110 !
b1001110 A
b1110 B
b100 @
1"
1#
#18900
0"
#19000
b1000100 !
b1000100 A
b10 @
b100 B
1"
#19100
0"
#19200
b1000010 !
b1000010 A
b0xxxxx @
b10 B
1"
