pratica 5/flipflopD/flipflop_d.v
module flipflop_D (D, clk, preset, clear, Q, QNot);

    input D, clk, preset, clear;
    output reg Q, QNot; 

    always @(negedge clk) begin
        case ({preset, clear})
            2'b01: Q = 0; 
            2'b10: Q = 1; 
            2'b00: begin  
                if (D) Q = 1;
                if (~D) Q = 0;
            end
            default: Q = 1'bX;
    endcase
        QNot = ~Q;
    end

endmodule

pratica 5/flipflopD/flpD_teste.v
`timescale 1ns/1ns
`include "flipflop_d.v"

module flpD_teste;

    reg  D, clk, preset, clear;
    wire Q, QNot;
    flipflop_D uut( D, clk, preset, clear, Q, QNot);

    initial begin
        $dumpfile("flpD_teste.vcd");
        $dumpvars(0, flpD_teste);

        {preset,clear,D} = 3'b000; #20;
        {preset,clear,D} = 3'b001; #20;
        {preset,clear,D} = 3'b010; #20;
        {preset,clear,D} = 3'b011; #20;
        {preset,clear,D} = 3'b100; #20;
        {preset,clear,D} = 3'b101; #20;
        {preset,clear,D} = 3'b110; #20;
        {preset,clear,D} = 3'b111; #20;

        $display("Teste completo");
        $finish;
    end

    initial begin
        clk = 0;
        forever #10 clk = ~clk ;
    end

endmodule

pratica 5/flipflopD/flpD_teste.vcd
$date
	Mon Nov 25 23:00:25 2024
$end
$version
	Icarus Verilog
$end
$timescale
	1ns
$end
$scope module flpD_teste $end
$var wire 1 ! QNot $end
$var wire 1 " Q $end
$var reg 1 # D $end
$var reg 1 $ clear $end
$var reg 1 % clk $end
$var reg 1 & preset $end
$scope module uut $end
$var wire 1 # D $end
$var wire 1 $ clear $end
$var wire 1 % clk $end
$var wire 1 & preset $end
$var reg 1 " Q $end
$var reg 1 ! QNot $end
$upscope $end
$upscope $end
$enddefinitions $end
$comment Show the parameter values. $end
$dumpall
$end
#0
$dumpvars
0&
0%
0$
0#
0"
1!
$end
#10
1%
#20
0!
1"
0%
1#
#30
1%
#40
1!
0"
0%
1$
0#
#50
1%
#60
0%
1#
#70
1%
#80
0!
1"
0%
1&
0$
0#
#90
1%
#100
0%
1#
#110
1%
#120
x!
x"
0%
1$
0#
#130
1%
#140
0%
1#
